grademage/__init__.py
grademage/grademage.py
grademage-0.1.6.dist-info/LICENSE
grademage-0.1.6.dist-info/METADATA
grademage-0.1.6.dist-info/WHEEL
grademage-0.1.6.dist-info/top_level.txt
grademage-0.1.6.dist-info/RECORD
