Metadata-Version: 2.1
Name: grademage
Version: 0.1.6
Summary: Module to grade online quiz.
Home-page: https://github.com/yiyitech/grademage
Author: Samuel Zhang
Author-email: qisamuelzhang@hotmail.com
License: MIT
Platform: UNKNOWN
License-File: LICENSE
Requires-Dist: requests
